{
	"configurations" : 
	[
		{
			"directories" : 
			[
				{
					"build" : ".",
					"childIndexes" : 
					[
						1,
						2
					],
					"minimumCMakeVersion" : 
					{
						"string" : "3.10"
					},
					"projectIndex" : 0,
					"source" : ".",
					"targetIndexes" : 
					[
						2,
						4,
						6,
						7
					]
				},
				{
					"build" : "src",
					"minimumCMakeVersion" : 
					{
						"string" : "3.10"
					},
					"parentIndex" : 0,
					"projectIndex" : 0,
					"source" : "src",
					"targetIndexes" : 
					[
						8
					]
				},
				{
					"build" : "test",
					"minimumCMakeVersion" : 
					{
						"string" : "3.10"
					},
					"parentIndex" : 0,
					"projectIndex" : 0,
					"source" : "test",
					"targetIndexes" : 
					[
						0,
						1,
						3,
						5,
						9
					]
				}
			],
			"name" : "",
			"projects" : 
			[
				{
					"directoryIndexes" : 
					[
						0,
						1,
						2
					],
					"name" : "Pine",
					"targetIndexes" : 
					[
						0,
						1,
						2,
						3,
						4,
						5,
						6,
						7,
						8,
						9
					]
				}
			],
			"targets" : 
			[
				{
					"directoryIndex" : 2,
					"id" : "ThreadPoolTest::@36f028580bb02cc8272a",
					"jsonFile" : "target-ThreadPoolTest-78871b5ab2fb4a5c41bc.json",
					"name" : "ThreadPoolTest",
					"projectIndex" : 0
				},
				{
					"directoryIndex" : 2,
					"id" : "build-tests::@36f028580bb02cc8272a",
					"jsonFile" : "target-build-tests-1030eb661c9147734bb1.json",
					"name" : "build-tests",
					"projectIndex" : 0
				},
				{
					"directoryIndex" : 0,
					"id" : "check-format::@6890427a1f51a3e7e1df",
					"jsonFile" : "target-check-format-46b4acfefac12e605e20.json",
					"name" : "check-format",
					"projectIndex" : 0
				},
				{
					"directoryIndex" : 2,
					"id" : "check-tests::@36f028580bb02cc8272a",
					"jsonFile" : "target-check-tests-f3ccd79661ef8e126249.json",
					"name" : "check-tests",
					"projectIndex" : 0
				},
				{
					"directoryIndex" : 0,
					"id" : "clang-tidy::@6890427a1f51a3e7e1df",
					"jsonFile" : "target-clang-tidy-c8f72486041e5fbdc8aa.json",
					"name" : "clang-tidy",
					"projectIndex" : 0
				},
				{
					"directoryIndex" : 2,
					"id" : "client::@36f028580bb02cc8272a",
					"jsonFile" : "target-client-71bd4ef9d68bc92934be.json",
					"name" : "client",
					"projectIndex" : 0
				},
				{
					"directoryIndex" : 0,
					"id" : "cpplint::@6890427a1f51a3e7e1df",
					"jsonFile" : "target-cpplint-6a8dc4961a217e8a7d70.json",
					"name" : "cpplint",
					"projectIndex" : 0
				},
				{
					"directoryIndex" : 0,
					"id" : "format::@6890427a1f51a3e7e1df",
					"jsonFile" : "target-format-c543ec61b12587eabf30.json",
					"name" : "format",
					"projectIndex" : 0
				},
				{
					"directoryIndex" : 1,
					"id" : "pine_shared::@145eef247bfb46b6828c",
					"jsonFile" : "target-pine_shared-22606ee47eed608e6865.json",
					"name" : "pine_shared",
					"projectIndex" : 0
				},
				{
					"directoryIndex" : 2,
					"id" : "server::@36f028580bb02cc8272a",
					"jsonFile" : "target-server-86b740ea56ba5cb69d69.json",
					"name" : "server",
					"projectIndex" : 0
				}
			]
		}
	],
	"kind" : "codemodel",
	"paths" : 
	{
		"build" : "/home/wuchengen/Desktop/MyWebserver/build",
		"source" : "/home/wuchengen/Desktop/MyWebserver"
	},
	"version" : 
	{
		"major" : 2,
		"minor" : 0
	}
}
